turkle/__init__.py
turkle/admin.py
turkle/apps.py
turkle/models.py
turkle/urls.py
turkle/utils.py
turkle/views.py
turkle/api/__init__.py
turkle/api/admin.py
turkle/api/serializers.py
turkle/api/urls.py
turkle/api/views.py
turkle/api/tests/__init__.py
turkle/api/tests/test_batches.py
turkle/api/tests/test_groups.py
turkle/api/tests/test_projects.py
turkle/api/tests/test_users.py
turkle/management/__init__.py
turkle/management/commands/__init__.py
turkle/management/commands/expire_assignments.py
turkle/migrations/0001_initial.py
turkle/migrations/0002_add_batch_level_permissions.py
turkle/migrations/0003_batch_custom_permissions.py
turkle/migrations/0004_batch_login_required.py
turkle/migrations/0005_batch_published.py
turkle/migrations/0006_copy_can_work_on_permission.py
turkle/migrations/0007_auto_20200702_1925.py
turkle/migrations/0008_fix_multi_assignment_anonymous_batches.py
turkle/migrations/0009_batch_completed.py
turkle/migrations/0010_project_allotted_assignment_time.py
turkle/migrations/0011_add_turkle_user_admin_group.py
turkle/migrations/0012_auto_20210923_1503.py
turkle/migrations/0013_activeproject_activeuser.py
turkle/migrations/__init__.py
turkle/static/favicon-16x16.png
turkle/static/favicon-32x32.png
turkle/static/admin/css/turkle-admin-theme.css
turkle/static/admin/js/turkle-admin.js
turkle/static/admin/js/turkle-file-upload.js
turkle/static/turkle/cal-heatmap-3.6.2.min.js
turkle/static/turkle/cal-heatmap.css
turkle/static/turkle/d3-3.5.17.min.js
turkle/static/turkle/jquery-3.3.1.min.js
turkle/static/turkle/jquery.countdown-2.2.0.js
turkle/static/turkle/parsley-2.9.1.min.js
turkle/static/turkle/bootstrap-4.1.3/css/bootstrap-grid.css
turkle/static/turkle/bootstrap-4.1.3/css/bootstrap-grid.css.map
turkle/static/turkle/bootstrap-4.1.3/css/bootstrap-grid.min.css
turkle/static/turkle/bootstrap-4.1.3/css/bootstrap-grid.min.css.map
turkle/static/turkle/bootstrap-4.1.3/css/bootstrap-reboot.css
turkle-3.1.0.dist-info/LICENSE
turkle-3.1.0.dist-info/METADATA
turkle-3.1.0.dist-info/WHEEL
turkle-3.1.0.dist-info/top_level.txt
turkle-3.1.0.dist-info/RECORD
