Metadata-Version: 2.1
Name: turkle
Version: 3.1.0
Summary: Django-based clone of Amazon's Mechanical Turk service
Home-page: https://github.com/hltcoe/turkle
Author: Craig Harman
Author-email: craig@craigharman.net
License: BSD
Project-URL: Documentation, https://turkle.readthedocs.io/
Keywords: annotation,crowdsourcing,mturk,mechanical turk
Classifier: Development Status :: 5 - Production/Stable
Classifier: Environment :: Web Environment
Classifier: Intended Audience :: Developers
Classifier: Intended Audience :: Science/Research
Classifier: License :: OSI Approved :: BSD License
Classifier: Natural Language :: English
Classifier: Programming Language :: Python :: 3
Requires-Python: >=3.8
License-File: LICENSE
Requires-Dist: beautifulsoup4
Requires-Dist: Django ~=4.2.23
Requires-Dist: django-admin-autocomplete-list-filter2 ==1.0.3
Requires-Dist: django-guardian ==2.4.0
Requires-Dist: djangorestframework ==3.15.2
Requires-Dist: drf-nested-routers ==0.94.2
Requires-Dist: humanfriendly
Requires-Dist: inflection
Requires-Dist: jsonfield ==3.1.0
Requires-Dist: uritemplate
